NiukeXiaozhaoMianshiJiqiaoZhinanFix1/README.md
NiukeXiaozhaoMianshiJiqiaoZhinanFix1/__init__.py
NiukeXiaozhaoMianshiJiqiaoZhinanFix1/__main__.py
NiukeXiaozhaoMianshiJiqiaoZhinanFix1/file.epub
NiukeXiaozhaoMianshiJiqiaoZhinanFix1/index.html
NiukeXiaozhaoMianshiJiqiaoZhinanFix1/css/__init__.py
NiukeXiaozhaoMianshiJiqiaoZhinanFix1/css/annotations.css
NiukeXiaozhaoMianshiJiqiaoZhinanFix1/css/main.css
NiukeXiaozhaoMianshiJiqiaoZhinanFix1/css/normalize.css
NiukeXiaozhaoMianshiJiqiaoZhinanFix1/css/popup.css
NiukeXiaozhaoMianshiJiqiaoZhinanFix1/font/__init__.py
NiukeXiaozhaoMianshiJiqiaoZhinanFix1/font/fontello.eot
NiukeXiaozhaoMianshiJiqiaoZhinanFix1/font/fontello.svg
NiukeXiaozhaoMianshiJiqiaoZhinanFix1/font/fontello.ttf
NiukeXiaozhaoMianshiJiqiaoZhinanFix1/font/fontello.woff
NiukeXiaozhaoMianshiJiqiaoZhinanFix1/img/__init__.py
NiukeXiaozhaoMianshiJiqiaoZhinanFix1/img/annotator-glyph-sprite.png
NiukeXiaozhaoMianshiJiqiaoZhinanFix1/img/annotator-icon-sprite.png
NiukeXiaozhaoMianshiJiqiaoZhinanFix1/img/apple-touch-icon.png
NiukeXiaozhaoMianshiJiqiaoZhinanFix1/img/cancelfullscreen.png
NiukeXiaozhaoMianshiJiqiaoZhinanFix1/img/close.png
NiukeXiaozhaoMianshiJiqiaoZhinanFix1/img/fullscreen.png
NiukeXiaozhaoMianshiJiqiaoZhinanFix1/img/loader.gif
NiukeXiaozhaoMianshiJiqiaoZhinanFix1/img/menu-icon.png
NiukeXiaozhaoMianshiJiqiaoZhinanFix1/img/save.png
NiukeXiaozhaoMianshiJiqiaoZhinanFix1/img/saved.png
NiukeXiaozhaoMianshiJiqiaoZhinanFix1/img/settings-s.png
NiukeXiaozhaoMianshiJiqiaoZhinanFix1/img/settings.png
NiukeXiaozhaoMianshiJiqiaoZhinanFix1/img/star.png
NiukeXiaozhaoMianshiJiqiaoZhinanFix1/js/__init__.py
NiukeXiaozhaoMianshiJiqiaoZhinanFix1/js/epub.js
NiukeXiaozhaoMianshiJiqiaoZhinanFix1/js/epub.min.js
NiukeXiaozhaoMianshiJiqiaoZhinanFix1/js/epub.min.map
NiukeXiaozhaoMianshiJiqiaoZhinanFix1/js/hooks.min.js
NiukeXiaozhaoMianshiJiqiaoZhinanFix1/js/hooks.min.map
NiukeXiaozhaoMianshiJiqiaoZhinanFix1/js/reader.js
NiukeXiaozhaoMianshiJiqiaoZhinanFix1/js/reader.js.map
niuke_xiaozhao_mianshi_jiqiao_zhinan_fix1-2025.3.25.1.dist-info/METADATA
niuke_xiaozhao_mianshi_jiqiao_zhinan_fix1-2025.3.25.1.dist-info/WHEEL
niuke_xiaozhao_mianshi_jiqiao_zhinan_fix1-2025.3.25.1.dist-info/entry_points.txt
niuke_xiaozhao_mianshi_jiqiao_zhinan_fix1-2025.3.25.1.dist-info/top_level.txt
niuke_xiaozhao_mianshi_jiqiao_zhinan_fix1-2025.3.25.1.dist-info/RECORD
